besepa/__init__.py
besepa/api.py
besepa/config.py
besepa/customers.py
besepa/exceptions.py
besepa/resource.py
besepa/util.py
besepa-0.3.2.dist-info/LICENSE
besepa-0.3.2.dist-info/METADATA
besepa-0.3.2.dist-info/WHEEL
besepa-0.3.2.dist-info/top_level.txt
besepa-0.3.2.dist-info/RECORD
