Metadata-Version: 2.1
Name: besepa
Version: 0.3.2
Summary: Simple python wrapper to Besepa.com's API.
Home-page: https://github.com/txerpa/besepa-python
Author: Mateu Cànaves
Author-email: mateu.canaves@gmail.com
Maintainer: Biel Massot
Maintainer-email: biel.massot@txerpa.com
License: MIT
Keywords: besepa,rest,sdk,debits,sepa
Platform: UNKNOWN
Classifier: Development Status :: 3 - Alpha
Classifier: Intended Audience :: Developers
Classifier: Operating System :: OS Independent
Classifier: Programming Language :: Python
Classifier: Programming Language :: Python :: 2
Classifier: Programming Language :: Python :: 2.7
Classifier: Programming Language :: Python :: 3
Classifier: Programming Language :: Python :: 3.5
Classifier: Programming Language :: Python :: 3.6
Classifier: Programming Language :: Python :: Implementation :: PyPy
Classifier: Topic :: Software Development :: Libraries :: Python Modules
Requires-Dist: requests (<3.0,>=2.22.0)
